{
  "atualizado_em": "2026-06-18T22:58:36Z",
  "fonte": {
    "base_url": "https://dadosabertos.ccee.org.br/api/3/action/datastore_search",
    "resource_id": "3f279d6b-1069-42f7-9b0a-217b084729c4",
    "limite": 32000
  },
  "hoje": {
    "data_iso": "2026-06-18",
    "data_br": "18/06/2026",
    "total_registros": 72,
    "linhas": [
      {
        "Hora": 0,
        "NORDESTE": 203.12,
        "SUDESTE": 203.13,
        "SUL": 203.13
      },
      {
        "Hora": 1,
        "NORDESTE": 202.68,
        "SUDESTE": 202.68,
        "SUL": 202.69
      },
      {
        "Hora": 2,
        "NORDESTE": 202.47,
        "SUDESTE": 202.48,
        "SUL": 202.48
      },
      {
        "Hora": 3,
        "NORDESTE": 202.06,
        "SUDESTE": 202.06,
        "SUL": 202.07
      },
      {
        "Hora": 4,
        "NORDESTE": 202.45,
        "SUDESTE": 202.46,
        "SUL": 202.46
      },
      {
        "Hora": 5,
        "NORDESTE": 202.71,
        "SUDESTE": 202.71,
        "SUL": 202.71
      },
      {
        "Hora": 6,
        "NORDESTE": 203.2,
        "SUDESTE": 203.21,
        "SUL": 203.21
      },
      {
        "Hora": 7,
        "NORDESTE": 202.42,
        "SUDESTE": 202.43,
        "SUL": 202.44
      },
      {
        "Hora": 8,
        "NORDESTE": 200.17,
        "SUDESTE": 200.18,
        "SUL": 200.19
      },
      {
        "Hora": 9,
        "NORDESTE": 179.74,
        "SUDESTE": 179.75,
        "SUL": 195.12
      },
      {
        "Hora": 10,
        "NORDESTE": 163.52,
        "SUDESTE": 163.53,
        "SUL": 186.25
      },
      {
        "Hora": 11,
        "NORDESTE": 182.83,
        "SUDESTE": 182.84,
        "SUL": 184.41
      },
      {
        "Hora": 12,
        "NORDESTE": 159.08,
        "SUDESTE": 159.09,
        "SUL": 159.1
      },
      {
        "Hora": 13,
        "NORDESTE": 193.93,
        "SUDESTE": 193.94,
        "SUL": 193.95
      },
      {
        "Hora": 14,
        "NORDESTE": 200.07,
        "SUDESTE": 200.08,
        "SUL": 200.08
      },
      {
        "Hora": 15,
        "NORDESTE": 202.69,
        "SUDESTE": 202.69,
        "SUL": 202.7
      },
      {
        "Hora": 16,
        "NORDESTE": 209.47,
        "SUDESTE": 209.47,
        "SUL": 209.47
      },
      {
        "Hora": 17,
        "NORDESTE": 223.02,
        "SUDESTE": 223.02,
        "SUL": 223.02
      },
      {
        "Hora": 18,
        "NORDESTE": 227.33,
        "SUDESTE": 227.34,
        "SUL": 227.34
      },
      {
        "Hora": 19,
        "NORDESTE": 220.01,
        "SUDESTE": 220.01,
        "SUL": 220.01
      },
      {
        "Hora": 20,
        "NORDESTE": 214.04,
        "SUDESTE": 214.05,
        "SUL": 214.05
      },
      {
        "Hora": 21,
        "NORDESTE": 210.05,
        "SUDESTE": 210.06,
        "SUL": 210.06
      },
      {
        "Hora": 22,
        "NORDESTE": 208.06,
        "SUDESTE": 208.07,
        "SUL": 208.07
      },
      {
        "Hora": 23,
        "NORDESTE": 205.32,
        "SUDESTE": 205.32,
        "SUL": 205.32
      }
    ]
  },
  "amanha": {
    "data_iso": "2026-06-19",
    "data_br": "19/06/2026",
    "total_registros": 72,
    "linhas": [
      {
        "Hora": 0,
        "NORDESTE": 201.32,
        "SUDESTE": 201.33,
        "SUL": 201.33
      },
      {
        "Hora": 1,
        "NORDESTE": 200.01,
        "SUDESTE": 200.01,
        "SUL": 200.02
      },
      {
        "Hora": 2,
        "NORDESTE": 199.37,
        "SUDESTE": 199.38,
        "SUL": 199.38
      },
      {
        "Hora": 3,
        "NORDESTE": 199.16,
        "SUDESTE": 199.17,
        "SUL": 199.17
      },
      {
        "Hora": 4,
        "NORDESTE": 199.38,
        "SUDESTE": 199.38,
        "SUL": 199.39
      },
      {
        "Hora": 5,
        "NORDESTE": 200.47,
        "SUDESTE": 200.48,
        "SUL": 200.49
      },
      {
        "Hora": 6,
        "NORDESTE": 200.97,
        "SUDESTE": 200.98,
        "SUL": 200.99
      },
      {
        "Hora": 7,
        "NORDESTE": 191.27,
        "SUDESTE": 199.91,
        "SUL": 199.92
      },
      {
        "Hora": 8,
        "NORDESTE": 57.31,
        "SUDESTE": 198.61,
        "SUL": 198.62
      },
      {
        "Hora": 9,
        "NORDESTE": 57.31,
        "SUDESTE": 85.65,
        "SUL": 197.26
      },
      {
        "Hora": 10,
        "NORDESTE": 57.31,
        "SUDESTE": 57.31,
        "SUL": 196.44
      },
      {
        "Hora": 11,
        "NORDESTE": 57.31,
        "SUDESTE": 57.31,
        "SUL": 195.89
      },
      {
        "Hora": 12,
        "NORDESTE": 57.31,
        "SUDESTE": 57.31,
        "SUL": 182.54
      },
      {
        "Hora": 13,
        "NORDESTE": 184.14,
        "SUDESTE": 184.15,
        "SUL": 195.37
      },
      {
        "Hora": 14,
        "NORDESTE": 199.89,
        "SUDESTE": 199.9,
        "SUL": 199.91
      },
      {
        "Hora": 15,
        "NORDESTE": 201.16,
        "SUDESTE": 201.17,
        "SUL": 201.18
      },
      {
        "Hora": 16,
        "NORDESTE": 207.21,
        "SUDESTE": 207.22,
        "SUL": 207.22
      },
      {
        "Hora": 17,
        "NORDESTE": 217.53,
        "SUDESTE": 217.54,
        "SUL": 217.54
      },
      {
        "Hora": 18,
        "NORDESTE": 222.43,
        "SUDESTE": 222.44,
        "SUL": 222.44
      },
      {
        "Hora": 19,
        "NORDESTE": 216.03,
        "SUDESTE": 216.04,
        "SUL": 216.04
      },
      {
        "Hora": 20,
        "NORDESTE": 209.56,
        "SUDESTE": 209.57,
        "SUL": 209.57
      },
      {
        "Hora": 21,
        "NORDESTE": 201.21,
        "SUDESTE": 201.22,
        "SUL": 201.22
      },
      {
        "Hora": 22,
        "NORDESTE": 200.59,
        "SUDESTE": 200.59,
        "SUL": 200.6
      },
      {
        "Hora": 23,
        "NORDESTE": 200.87,
        "SUDESTE": 200.87,
        "SUL": 200.88
      }
    ]
  }
}